theconn/__init__.py
theconn/cli.py
theconn/github.py
theconn/py.typed
theconn/version.py
theconn/commands/__init__.py
theconn/commands/check.py
theconn/commands/init.py
theconn/commands/uninstall.py
theconn/commands/update.py
theconn-0.2.0.dist-info/METADATA
theconn-0.2.0.dist-info/WHEEL
theconn-0.2.0.dist-info/entry_points.txt
theconn-0.2.0.dist-info/RECORD
