Metadata-Version: 2.4
Name: theconn
Version: 0.2.0
Summary: The Conn - AI-powered development framework CLI
Project-URL: Homepage, https://github.com/Lockeysama/TheConn
Project-URL: Documentation, https://github.com/Lockeysama/TheConn/blob/main/CLI.md
Project-URL: Repository, https://github.com/Lockeysama/TheConn
Project-URL: Issues, https://github.com/Lockeysama/TheConn/issues
Project-URL: Changelog, https://github.com/Lockeysama/TheConn/releases
Author-email: Lockeysama <196349143@qq.com>
License: MIT
Keywords: ai,cli,development,framework,theconn
Requires-Python: >=3.12
Requires-Dist: click>=8.1.0
Requires-Dist: requests>=2.31.0
Requires-Dist: rich>=13.0.0
